{
  "$schema": "../../resources/schema-metadata-draft.json",
  "project": {
    "__type": "Project",
    "howToCite": "Marti, P., Studer, D., Affolter, S. (2024). Globalgeschichtliche Perspektiven im Schweizer Geschichtsunterricht [Dataset]. DaSCH. https://ark.dasch.swiss/ark:/72163/1/084A",
    "teaserText": "Das Forschungsprojekt liefert empirische Ergebnisse auf breiter Basis zu Potentialen von globalgeschichtlichen Perspektiven im Geschichtsunterricht.",
    "datasets": [
      "http://ns.dasch.swiss/repository#dsp-084A-dataset-000"
    ],
    "contactPoint": "http://ns.dasch.swiss/repository#dsp-084A-person-000",
    "description": {
      "de": "Für Geschichtslernen, das zur Orientierung in der Lebenswelt heutiger Lernender beitragen soll, ist die Einsicht in die historischen Hintergründe von Gegenwartsphänomenen wie der Globalisierung, Migration und gesellschaftlicher Heterogenität sehr bedeutsam. Als fachwissenschaftlicher Zugang bietet sich der Ansatz der Globalgeschichte an. Dieser wird in der Geschichtsdidaktik diskutiert, ist dort empirisch aber bislang wenig erforscht. Die Studie setzt an dieser Lücke an. Sie ist im Geschichtsunterricht der gymnasialen Sekundarstufe II angesiedelt und methodisch der partizipativen Praxisforschung zugeordnet. Gemeinsam mit Lehrpersonen werden Unterrichtseinheiten entwickelt und die so angestossene Unterrichtsentwicklung durch video-, interview- und fragebogenbasierte Erhebungen empirisch untersucht."
    },
    "disciplines": [
      {
        "de": "10104 Erziehungs- und Bildungswissenschaften, Fachdidaktiken"
      },
      {
        "de": "10301 Allgemeine Geschichte (ohne Ur- und Frühgeschichte)"
      }
    ],
    "endDate": "2024-02-29",
    "funders": [
      "http://ns.dasch.swiss/repository#dsp-084A-organization-001"
    ],
    "grants": [
      "http://ns.dasch.swiss/repository#dsp-084A-grant-000"
    ],
    "keywords": [
      {
        "de": "Geschichtsdidaktik"
      },
      {
        "de": "Geschichtsunterricht"
      },
      {
        "de": "Globalgeschichte"
      },
      {
        "de": "Partizipative Unterrichtsentwicklung"
      },
      {
        "de": "Praxisforschung"
      },
      {
        "de": "Sekundarstufe II"
      },
      {
        "de": "Videoanalyse"
      }
    ],
    "name": "Globalgeschichtliche Perspektiven im Schweizer Geschichtsunterricht",
    "publications": [
      {
        "text": "",
        "url": [
          {
            "__type": "URL",
            "type": "URL",
            "url": "https://irf.fhnw.ch/handle/11654/31495",
            "text": "https://irf.fhnw.ch/handle/11654/31495"
          }
        ]
      }
    ],
    "shortcode": "084A",
    "spatialCoverage": [
      {
        "__type": "URL",
        "type": "Geonames",
        "url": "https://www.geonames.org/2658434/switzerland.html",
        "text": "Switzerland"
      }
    ],
    "startDate": "2020-07-01",
    "temporalCoverage": [
      {
        "en": "21. Jhd."
      }
    ],
    "url": {
      "__type": "URL",
      "type": "URL",
      "url": "https://app.dasch.swiss/project/iM_un1y7SVa-Fny6yN51-A",
      "text": "Discover Project Data"
    },
    "secondaryURL": {
      "__type": "URL",
      "type": "URL",
      "url": "https://irf.fhnw.ch/handle/11654/31495",
      "text": "External Project Website"
    },
    "status": "Ongoing"
  },
  "datasets": [
    {
      "__id": "http://ns.dasch.swiss/repository#dsp-084A-dataset-000",
      "__type": "Dataset",
      "abstracts": [
        {
          "de": "Das Dataset beinhaltet im Projekt erhobene Daten aus Lehrer:innen- und Schüler:innenperspektive: Transkripte der «Stimulated Recall»-Interviews, Transkripte der Eingangsinterviews, soziodemographische Angaben, Fragebögen der Schüler:innen sowie die Dokumentation der entsprechenden Erhebungsinstrumente."
        }
      ],
      "accessConditions": "closed",
      "howToCite": "Marti, P., Studer, D., Affolter, S. (2024). Globalgeschichtliche Perspektiven im Schweizer Geschichtsunterricht [Dataset]. DaSCH. https://ark.dasch.swiss/ark:/72163/1/084A",
      "languages": [
        {
          "de": "Deutsch",
          "en": "German",
          "fr": "allemand"
        }
      ],
      "licenses": [
        {
          "__type": "License",
          "date": "2024-02-21",
          "license": {
            "__type": "URL",
            "type": "Creative Commons",
            "url": "https://creativecommons.org/licenses/by-sa/4.0/",
            "text": "CC BY-SA 4.0"
          }
        }
      ],
      "attributions": [
        {
          "__type": "Attribution",
          "agent": "http://ns.dasch.swiss/repository#dsp-084A-person-000",
          "roles": [
            "Projektleitung"
          ]
        },
        {
          "__type": "Attribution",
          "agent": "http://ns.dasch.swiss/repository#dsp-084A-person-001",
          "roles": [
            "Projektmitarbeit"
          ]
        },
        {
          "__type": "Attribution",
          "agent": "http://ns.dasch.swiss/repository#dsp-084A-person-002",
          "roles": [
            "Projektmitarbeit"
          ]
        }
      ],
      "status": "Ongoing",
      "title": "Globalgeschichtliche Perspektiven im Schweizer Geschichtsunterricht",
      "typeOfData": [
        "Text"
      ]
    }
  ],
  "persons": [
    {
      "__id": "http://ns.dasch.swiss/repository#dsp-084A-person-001",
      "__type": "Person",
      "email": "dominic.studer@fhnw.ch",
      "familyNames": [
        "Studer"
      ],
      "givenNames": [
        "Dominic"
      ],
      "jobTitles": [
        "Wissenschaftlicher Mitarbeiter"
      ],
      "affiliation": [
        "http://ns.dasch.swiss/repository#dsp-084A-organization-000"
      ],
      "authorityRefs": [
        {
          "__type": "URL",
          "type": "ORCID",
          "url": "https://orcid.org/0000-0003-4079-7387",
          "text": "ORCID URL: https://orcid.org/0000-0003-4079-7387"
        }
      ]
    },
    {
      "__id": "http://ns.dasch.swiss/repository#dsp-084A-person-002",
      "__type": "Person",
      "email": "simon.affolter@fhnw.ch",
      "familyNames": [
        "Affolter"
      ],
      "givenNames": [
        "Simon"
      ],
      "jobTitles": [
        "Wissenschaftlicher Mitarbeiter"
      ],
      "affiliation": [
        "http://ns.dasch.swiss/repository#dsp-084A-organization-000"
      ],
      "authorityRefs": [
        {
          "__type": "URL",
          "type": "ORCID",
          "url": "https://orcid.org/0000-0002-5668-7695",
          "text": "ORCID URL: https://orcid.org/0000-0002-5668-7695"
        }
      ]
    },
    {
      "__id": "http://ns.dasch.swiss/repository#dsp-084A-person-000",
      "__type": "Person",
      "email": "philipp.marti@fhnw.ch",
      "familyNames": [
        "Marti"
      ],
      "givenNames": [
        "Philipp"
      ],
      "jobTitles": [
        "Wissenschaftlicher Mitarbeiter"
      ],
      "affiliation": [
        "http://ns.dasch.swiss/repository#dsp-084A-organization-000"
      ]
    }
  ],
  "organizations": [
    {
      "__id": "http://ns.dasch.swiss/repository#dsp-084A-organization-001",
      "__type": "Organization",
      "name": "Swiss National Science Foundation (SNSF)",
      "url": {
        "__type": "URL",
        "type": "URL",
        "url": "https://www.snf.ch",
        "text": "https://www.snf.ch"
      }
    },
    {
      "__id": "http://ns.dasch.swiss/repository#dsp-084A-organization-000",
      "__type": "Organization",
      "name": "Pädagogische Hochschule der Fachhochschule Nordwestschweiz",
      "url": {
        "__type": "URL",
        "type": "URL",
        "url": "https://www.fhnw.ch/de/die-fhnw/hochschulen/ph",
        "text": "https://www.fhnw.ch/de/die-fhnw/hochschulen/ph"
      }
    }
  ],
  "grants": [
    {
      "__id": "http://ns.dasch.swiss/repository#dsp-084A-grant-000",
      "__type": "Grant",
      "funders": [
        "http://ns.dasch.swiss/repository#dsp-084A-organization-001"
      ],
      "name": "Project funding",
      "number": "192169",
      "url": {
        "__type": "URL",
        "type": "URL",
        "url": "https://data.snf.ch/grants/grant/192169",
        "text": "https://data.snf.ch/grants/grant/192169"
      }
    }
  ]
}
