{
    "id": "0112-record-020",
    "pid": "https://ark.dasch.swiss/ark:/72163/1/0112-record-020",
    "label": {
        "en": "minus_question.png"
    },
    "accessRights": {
        "accessRights": "Full Open Access"
    },
    "legalInfo": [
        {
            "license": {
                "licenseIdentifier": "CC BY-SA 4.0",
                "licenseDate": "2021-09-02",
                "licenseURI": "https://creativecommons.org/licenses/by-sa/4.0/"
            },
            "copyrightHolder": "0112-organization-001",
            "authorship": [
                "0112-person-000",
                "0112-person-001",
                "0112-person-002",
                "0112-person-003",
                "0112-person-004"
            ]
        }
    ],
    "howToCite": "minus_question.png (2021). [Data Record]. DaSCH. https://ark.dasch.swiss/ark:/72163/1/0112-record-020",
    "publisher": "DaSCH",
    "typeOfData": "Image",
    "dateCreated": "2020-01-24",
    "datePublished": "2021-08-28",
    "size": "275.6 MB",
    "dateModified": "2021-06-17",
    "keywords": [
        {
            "en": "depulso"
        }
    ],
    "source": "Eveniet demergo textor astrum beatae uter necessitatibus nihil adnuo vociferor."
}
