{
    "id": "0801-record-023",
    "pid": "https://ark.dasch.swiss/ark:/72163/1/0801-record-023",
    "label": {
        "en": "swiftly_hype_on.png"
    },
    "accessRights": {
        "accessRights": "Full Open Access"
    },
    "legalInfo": [
        {
            "license": {
                "licenseIdentifier": "CC BY-NC-SA 4.0",
                "licenseDate": "2021-09-02",
                "licenseURI": "https://creativecommons.org/licenses/by-nc-sa/4.0/"
            },
            "copyrightHolder": "0801-organization-000",
            "authorship": [
                "0801-person-000",
                "0801-person-001",
                "0801-person-004",
                "0801-person-005",
                "0801-person-000"
            ]
        },
        {
            "license": {
                "licenseIdentifier": "CC BY-NC-SA 4.0",
                "licenseDate": "2021-09-02",
                "licenseURI": "https://creativecommons.org/licenses/by-nc-sa/4.0/"
            },
            "copyrightHolder": "0801-organization-000",
            "authorship": [
                "0801-person-000",
                "0801-person-001",
                "0801-person-004",
                "0801-person-005",
                "0801-person-000"
            ]
        },
        {
            "license": {
                "licenseIdentifier": "CC BY-NC-SA 4.0",
                "licenseDate": "2021-09-02",
                "licenseURI": "https://creativecommons.org/licenses/by-nc-sa/4.0/"
            },
            "copyrightHolder": "0801-organization-000",
            "authorship": [
                "0801-person-000",
                "0801-person-001",
                "0801-person-004",
                "0801-person-005",
                "0801-person-000"
            ]
        },
        {
            "license": {
                "licenseIdentifier": "CC BY-NC-SA 4.0",
                "licenseDate": "2021-09-02",
                "licenseURI": "https://creativecommons.org/licenses/by-nc-sa/4.0/"
            },
            "copyrightHolder": "0801-organization-000",
            "authorship": [
                "0801-person-000",
                "0801-person-001",
                "0801-person-004",
                "0801-person-005",
                "0801-person-000"
            ]
        }
    ],
    "howToCite": "swiftly_hype_on.png (2019). [Data Record]. DaSCH. https://ark.dasch.swiss/ark:/72163/1/0801-record-023",
    "publisher": "DaSCH",
    "typeOfData": "Image",
    "dateCreated": "2018-01-03",
    "datePublished": "2019-09-12",
    "size": "181.9 MB",
    "dateModified": "2019-03-29"
}
