{
    "id": "person-153",
    "pid": "MISSING",
    "sameAs": [
        {
            "type": "URL",
            "url": "https://erdw.ethz.ch/personen/profil.MTY5MzUy.TGlzdC83NzMsOTI0MjA1OTI2.html",
            "text": "https://erdw.ethz.ch/personen/profil.MTY5MzUy.TGlzdC83NzMsOTI0MjA1OTI2.html"
        }
    ],
    "givenNames": [
        "Martin"
    ],
    "familyNames": [
        "Ziegler"
    ],
    "jobTitles": [
        "Engineering Geologist"
    ],
    "affiliations": [
        "organization-061"
    ]
}