{
    "id": "person-352",
    "pid": "https://ark.dasch.swiss/ark:/72163/1/person-352",
    "sameAs": [
        {
            "type": "ORCID",
            "url": "https://orcid.org/0000-0002-0904-7177",
            "text": "ORCID URL: https://orcid.org/0000-0002-0904-7177"
        }
    ],
    "givenNames": [
        "Tiziana"
    ],
    "familyNames": [
        "Lombardo"
    ],
    "jobTitles": [
        "Conservation scientist"
    ],
    "affiliations": [
        "organization-126"
    ],
    "email": "tiziana.lombardo@nationalmuseum.ch"
}
