{
    "id": "080E",
    "pid": "MISSING",
    "name": "Digital Lexicon Iconographicum Mythologiae Classicae (Digital LIMC)",
    "shortcode": "080E",
    "officialName": "MISSING",
    "status": "Ongoing",
    "shortDescription": "Digital LIMC contains what we know about the iconography of Greek, Etruscan and Roman mythology, both in ancient Greek, Etruscan and Roman art as well as in neighbouring Mediterranean cultures.",
    "description": {
        "en": "Digital LIMC is a digital platform for Classical Mythology, it contains what we know about the iconography of Greek, Etruscan and Roman mythology, both in ancient Greek, Etruscan and Roman art as well as in the one of neighbouring Mediterranean cultures. These literary and iconographical sources of ancient mythology are key elements of the cultural heritage of mankind. The Foundation for the LIMC prepared and published 10 volumes of the Lexicon Iconographicum Mythologiae Classicae (LIMC) between 1981 and 2009. This publication project was followed by the Thesaurus Cultus et Rituum Antiquorum (ThesCRA; 10 volumes), focussing on ritual and cult in antiquity.\n\nDigital LIMC makes all data accessible which were assembled in the course of the preparation of the printed books and which are stored in the basement of a building of the University of Basel today."
    },
    "startDate": "2014-06-02",
    "endDate": "MISSING",
    "url": [
        "https://app.dasch.swiss/project/BRwvcfLLT72IN-fXzQkrdQ",
        "https://weblimc.org"
    ],
    "howToCite": "Digital LIMC (2021): Digital LIMC [database], DaSCH. https://ark.dasch.swiss/ark:/72163/1/080E.",
    "accessRights": {
        "accessRights": "Full Open Access"
    },
    "legalInfo": [
        {
            "license": {
                "licenseIdentifier": "CC BY-NC 4.0",
                "licenseDate": "2021-09-02",
                "licenseURI": "https://creativecommons.org/licenses/by-nc/4.0/"
            },
            "copyrightHolder": "MISSING",
            "authorship": [
                "MISSING"
            ]
        }
    ],
    "dataManagementPlan": "not accessible",
    "typeOfData": [
        "Image",
        "Text"
    ],
    "dataLanguage": [
        {
            "de": "Deutsch",
            "en": "German",
            "fr": "allemand"
        },
        {
            "de": "Englisch",
            "en": "English",
            "fr": "anglais"
        },
        {
            "de": "Französisch",
            "en": "French",
            "fr": "français"
        },
        {
            "de": "Italienisch",
            "en": "Italian",
            "fr": "italien"
        },
        {
            "en": "Greek"
        }
    ],
    "keywords": [
        {
            "en": "Archaeology"
        },
        {
            "en": "Egypt"
        },
        {
            "en": "Etruria"
        },
        {
            "en": "Greece"
        },
        {
            "en": "Mythology"
        },
        {
            "en": "Near East"
        },
        {
            "en": "Roman"
        }
    ],
    "disciplines": [
        {
            "type": "Skos",
            "url": "http://skos.um.es/unesco6/550501",
            "text": "Archaeology"
        }
    ],
    "temporalCoverage": [
        {
            "type": "Chronontology",
            "url": "http://chronontology.dainst.org/period/3mQhHXhO86oj",
            "text": "Near Eastern (Early Western World)"
        },
        {
            "type": "Chronontology",
            "url": "http://chronontology.dainst.org/period/yY1zReDz86zF",
            "text": "Roman (ancient Italian culture or period)"
        },
        {
            "type": "Chronontology",
            "url": "http://chronontology.dainst.org/period/6VooUMYGJjOI",
            "text": "Egyptian (ancient)"
        },
        {
            "type": "Chronontology",
            "url": "http://chronontology.dainst.org/period/YOyP9TLDuhrb",
            "text": "Ancient Greek (culture or style)"
        },
        {
            "type": "Chronontology",
            "url": "http://chronontology.dainst.org/period/RGbECa9kHJT4",
            "text": "Etruscan (culture or style)"
        }
    ],
    "spatialCoverage": [
        {
            "type": "Geonames",
            "url": "https://www.geonames.org/6255148",
            "text": "Europe"
        },
        {
            "type": "Geonames",
            "url": "https://www.geonames.org/7729887",
            "text": "Northern Africa"
        },
        {
            "type": "Geonames",
            "url": "https://www.geonames.org/6255147",
            "text": "Asia"
        }
    ],
    "attributions": [
        {
            "contributor": "080E-organization-005",
            "contributorType": [
                "publisher"
            ]
        }
    ],
    "abstract": {
        "en": "Digital LIMC makes accessible what we know about the iconography of Greek, Etruscan and Roman mythology in ancient Greek, Etruscan and Roman art as well as in the one of the neighbouring civilisations of the Mediterranean, to all people interested in classical antiquity. It contains basic information about more than 55’000 archaeological objects (e.g. vases, sculpture, gems, mosaics) which were assembled in the course of the preparation of the printed books of the LIMC and the ThesCRA from about 1970 onward. Short keyword type object descriptions and links to other research projects or museum databases will be added continuously as far as funds permit. The images of the objects are accessible online if the owning institution has given us permission for diffusion."
    },
    "funding": [
        {
            "funders": [
                "080E-organization-000"
            ]
        },
        {
            "funders": [
                "080E-organization-001"
            ],
            "name": "Program Support Education",
            "url": "https://www.snf.org/en/grants/grantees/u/university-of-basel/department-of-ancient-civilisations-program-support/"
        },
        {
            "funders": [
                "080E-organization-002"
            ],
            "number": "2015-2371/1.2",
            "name": "Gesuch im Bereich Bildung und Wissenschaft",
            "url": "http://www.ernst-goehner-stiftung.ch/index.php/de"
        },
        {
            "funders": [
                "080E-organization-003"
            ],
            "number": "14/17-18",
            "name": "Ceramica Stiftung",
            "url": "https://ceramica-ch.ch/"
        },
        {
            "funders": [
                "080E-organization-004"
            ],
            "number": "19-109",
            "name": "Gesuch im Bereich Kultur",
            "url": "https://www.binding-stiftung.ch/"
        }
    ],
    "alternativeNames": [
        {
            "en": "Digital LIMC"
        }
    ]
}