{
    "id": "0807-record-051",
    "pid": "https://ark.dasch.swiss/ark:/72163/1/0807-record-051",
    "label": {
        "en": "huzzah_dishearten.xml"
    },
    "accessRights": {
        "accessRights": "Full Open Access"
    },
    "legalInfo": [
        {
            "license": {
                "licenseIdentifier": "CC BY-NC-SA 4.0",
                "licenseDate": "2022-05-09",
                "licenseURI": "https://creativecommons.org/licenses/by-nc-sa/4.0/"
            },
            "copyrightHolder": "0807-organization-000",
            "authorship": [
                "0807-person-004",
                "0807-person-003",
                "0807-person-005",
                "0807-person-006",
                "0807-person-007"
            ]
        }
    ],
    "howToCite": "huzzah_dishearten.xml (2017). [Data Record]. DaSCH. https://ark.dasch.swiss/ark:/72163/1/0807-record-051",
    "publisher": "DaSCH",
    "typeOfData": "XML",
    "dateCreated": "2014-08-10",
    "datePublished": "2017-04-27",
    "size": "102.7 MB",
    "keywords": [
        {
            "en": "solus"
        }
    ]
}
