{
    "id": "0101-record-003",
    "pid": "https://ark.dasch.swiss/ark:/72163/1/0101-record-003",
    "label": {
        "en": "frilly.txt"
    },
    "accessRights": {
        "accessRights": "Embargoed Access"
    },
    "legalInfo": [
        {
            "license": {
                "licenseIdentifier": "CC BY-SA 4.0",
                "licenseDate": "2021-09-02",
                "licenseURI": "https://creativecommons.org/licenses/by-sa/4.0/"
            },
            "copyrightHolder": "0101-organization-000",
            "authorship": [
                "0101-person-000",
                "0101-person-001",
                "0101-person-002"
            ]
        }
    ],
    "howToCite": "frilly.txt (2019). [Data Record]. DaSCH. https://ark.dasch.swiss/ark:/72163/1/0101-record-003",
    "publisher": "DaSCH",
    "typeOfData": "Text",
    "dateCreated": "2018-04-16",
    "datePublished": "2019-05-08",
    "size": "101.3 MB",
    "description": {
        "en": "Cupiditate tribuo et copiose. Degusto uter facilis amitto umquam. Blanditiis dignissimos temeritas consequuntur circumvenio."
    }
}
