{
    "id": "084B-record-015",
    "pid": "https://ark.dasch.swiss/ark:/72163/1/084B-record-015",
    "label": {
        "en": "weird_unaware.pdf"
    },
    "accessRights": {
        "accessRights": "Open Access with Restrictions"
    },
    "legalInfo": [
        {
            "license": {
                "licenseIdentifier": "CC BY-SA 4.0",
                "licenseDate": "2025-07-08",
                "licenseURI": "https://creativecommons.org/licenses/by-sa/4.0"
            },
            "copyrightHolder": "084B-organization-001",
            "authorship": [
                "084B-person-001",
                "084B-person-000"
            ]
        }
    ],
    "howToCite": "weird_unaware.pdf (2024). [Data Record]. DaSCH. https://ark.dasch.swiss/ark:/72163/1/084B-record-015",
    "publisher": "DaSCH",
    "typeOfData": "Text",
    "dateCreated": "2023-03-07",
    "datePublished": "2024-01-09",
    "size": "35.6 MB"
}
