{
    "id": "082D-record-053",
    "pid": "https://ark.dasch.swiss/ark:/72163/1/082D-record-053",
    "label": {
        "en": "badly.txt"
    },
    "accessRights": {
        "accessRights": "Open Access with Restrictions"
    },
    "legalInfo": [
        {
            "license": {
                "licenseIdentifier": "CC BY-NC-SA 4.0",
                "licenseDate": "2021-09-02",
                "licenseURI": "https://creativecommons.org/licenses/by-nc-sa/4.0/"
            },
            "copyrightHolder": "082D-organization-001",
            "authorship": [
                "082D-person-001",
                "082D-person-002"
            ]
        }
    ],
    "howToCite": "badly.txt (2020). [Data Record]. DaSCH. https://ark.dasch.swiss/ark:/72163/1/082D-record-053",
    "publisher": "DaSCH",
    "typeOfData": "Text",
    "dateCreated": "2018-12-12",
    "datePublished": "2020-04-24",
    "size": "419.9 MB",
    "description": {
        "en": "Stabilis cum nihil. Abbas comitatus cubo tertius quos benigne utique ter quam. Degusto clamo curiositas benevolentia."
    },
    "source": "Spiritus eaque ambitus alter."
}
