{
    "id": "0848-record-035",
    "pid": "https://ark.dasch.swiss/ark:/72163/1/0848-record-035",
    "label": {
        "en": "sorrowful_perfumed_rebuff.txt"
    },
    "accessRights": {
        "accessRights": "Full Open Access"
    },
    "legalInfo": [
        {
            "license": {
                "licenseIdentifier": "CC BY-NC 4.0",
                "licenseDate": "2023-07-03",
                "licenseURI": "https://creativecommons.org/licenses/by-nc/4.0/"
            },
            "copyrightHolder": "0848-organization-001",
            "authorship": [
                "0848-person-000",
                "0848-person-001",
                "0848-person-002",
                "0848-person-003"
            ]
        }
    ],
    "howToCite": "sorrowful_perfumed_rebuff.txt (2022). [Data Record]. DaSCH. https://ark.dasch.swiss/ark:/72163/1/0848-record-035",
    "publisher": "DaSCH",
    "typeOfData": "Text",
    "dateCreated": "2022-05-22",
    "datePublished": "2022-12-12",
    "size": "225.6 MB",
    "dateModified": "2022-05-23",
    "description": {
        "en": "Amo sophismata vito cedo valeo tendo venio. Desolo ait cubicularis despecto facilis desipio conqueror vinum volup centum. Considero deprecator valde statua quos vomer tertius socius."
    },
    "keywords": [
        {
            "en": "aqua"
        },
        {
            "en": "beneficium"
        }
    ]
}
