{
    "id": "080C-record-020",
    "pid": "https://ark.dasch.swiss/ark:/72163/1/080C-record-020",
    "label": {
        "en": "tightly.png"
    },
    "accessRights": {
        "accessRights": "Full Open Access"
    },
    "legalInfo": [
        {
            "license": {
                "licenseIdentifier": "CC BY-NC 4.0",
                "licenseDate": "2023-12-07",
                "licenseURI": "https://creativecommons.org/licenses/by-nc/4.0/deed.en"
            },
            "copyrightHolder": "080C-organization-001",
            "authorship": [
                "080C-person-001",
                "080C-person-002",
                "080C-person-003",
                "080C-person-000"
            ]
        }
    ],
    "howToCite": "tightly.png (2021). [Data Record]. DaSCH. https://ark.dasch.swiss/ark:/72163/1/080C-record-020",
    "publisher": "DaSCH",
    "typeOfData": "Image",
    "dateCreated": "2021-03-07",
    "datePublished": "2021-06-20",
    "size": "159.0 MB",
    "keywords": [
        {
            "en": "acceptus"
        },
        {
            "en": "abundans"
        }
    ]
}
