{
    "id": "080C-record-038",
    "pid": "https://ark.dasch.swiss/ark:/72163/1/080C-record-038",
    "label": {
        "en": "and_boo.xml"
    },
    "accessRights": {
        "accessRights": "Full Open Access"
    },
    "legalInfo": [
        {
            "license": {
                "licenseIdentifier": "CC BY-NC 4.0",
                "licenseDate": "2023-12-07",
                "licenseURI": "https://creativecommons.org/licenses/by-nc/4.0/deed.en"
            },
            "copyrightHolder": "080C-organization-001",
            "authorship": [
                "080C-person-001",
                "080C-person-002",
                "080C-person-003",
                "080C-person-000"
            ]
        }
    ],
    "howToCite": "and_boo.xml (2021). [Data Record]. DaSCH. https://ark.dasch.swiss/ark:/72163/1/080C-record-038",
    "publisher": "DaSCH",
    "typeOfData": "XML",
    "dateCreated": "2019-01-14",
    "datePublished": "2021-05-23",
    "size": "319.5 MB",
    "keywords": [
        {
            "en": "abutor"
        }
    ]
}
